XStatic_angular_ui-0.4.0.1-py2.7-nspkg.pth
xstatic/pkg/angular_ui/__init__.py
xstatic/pkg/angular_ui/data/.bower.json
xstatic/pkg/angular_ui/data/.gitignore
xstatic/pkg/angular_ui/data/.travis.yml
xstatic/pkg/angular_ui/data/CHANGELOG.md
xstatic/pkg/angular_ui/data/grunt.js
xstatic/pkg/angular_ui/data/LICENSE
xstatic/pkg/angular_ui/data/package.json
xstatic/pkg/angular_ui/data/README.md
xstatic/pkg/angular_ui/data/build/angular-ui-ieshiv.js
xstatic/pkg/angular_ui/data/build/angular-ui-ieshiv.min.js
xstatic/pkg/angular_ui/data/build/angular-ui.css
xstatic/pkg/angular_ui/data/build/angular-ui.js
xstatic/pkg/angular_ui/data/build/angular-ui.min.css
xstatic/pkg/angular_ui/data/build/angular-ui.min.js
xstatic/pkg/angular_ui/data/common/module.js
xstatic/pkg/angular_ui/data/common/ieshiv/ieshiv.js
xstatic/pkg/angular_ui/data/common/ieshiv/README.md
xstatic/pkg/angular_ui/data/common/stylesheets/angular-ui.less
xstatic/pkg/angular_ui/data/common/stylesheets/mixins.less
xstatic/pkg/angular_ui/data/modules/directives/animate/animate.js
xstatic/pkg/angular_ui/data/modules/directives/animate/test/animateSpec.js
xstatic/pkg/angular_ui/data/modules/directives/calendar/calendar.js
xstatic/pkg/angular_ui/data/modules/directives/calendar/dependencies.json
xstatic/pkg/angular_ui/data/modules/directives/calendar/test/calendarSpec.js
xstatic/pkg/angular_ui/data/modules/directives/codemirror/codemirror.js
xstatic/pkg/angular_ui/data/modules/directives/codemirror/dependencies.json
xstatic/pkg/angular_ui/data/modules/directives/codemirror/test/codemirrorSpec.js
xstatic/pkg/angular_ui/data/modules/directives/currency/currency.js
xstatic/pkg/angular_ui/data/modules/directives/currency/README.md
xstatic/pkg/angular_ui/data/modules/directives/currency/stylesheets/currency.less
xstatic/pkg/angular_ui/data/modules/directives/currency/test/currencySpec.js
xstatic/pkg/angular_ui/data/modules/directives/date/date.js
XStatic_angular_ui-0.4.0.1.dist-info/DESCRIPTION.rst
XStatic_angular_ui-0.4.0.1.dist-info/METADATA
XStatic_angular_ui-0.4.0.1.dist-info/metadata.json
XStatic_angular_ui-0.4.0.1.dist-info/namespace_packages.txt
XStatic_angular_ui-0.4.0.1.dist-info/RECORD
XStatic_angular_ui-0.4.0.1.dist-info/top_level.txt
XStatic_angular_ui-0.4.0.1.dist-info/WHEEL
