Metadata-Version: 2.0
Name: XStatic-angular-ui
Version: 0.4.0.1
Summary: angular-ui 0.4.0 (XStatic packaging standard)
Home-page: https://github.com/angular-ui/angular-ui
Author: Richard Jones
Author-email: r1chardj0n3s@gmail.com
License: (same as angular-ui)
Keywords: angular_ui xstatic
Platform: any
